bahub/__init__.py
bahub/bahubapp/__init__.py
bahub/bahubapp/app.py
bahub/bahubapp/exceptions.py
bahub/bahubapp/result.py
bahub/bahubapp/controller/__init__.py
bahub/bahubapp/controller/backup.py
bahub/bahubapp/controller/list.py
bahub/bahubapp/controller/recover.py
bahub/bahubapp/controller/restore.py
bahub/bahubapp/controller/snapshot.py
bahub/bahubapp/entity/__init__.py
bahub/bahubapp/entity/access.py
bahub/bahubapp/entity/definition.py
bahub/bahubapp/entity/encryption.py
bahub/bahubapp/entity/recovery.py
bahub/bahubapp/handler/__init__.py
bahub/bahubapp/handler/abstractdocker.py
bahub/bahubapp/handler/commandoutputbackup.py
bahub/bahubapp/handler/dockeroutputbackup.py
bahub/bahubapp/handler/dockervolumebackup.py
bahub/bahubapp/handler/localfilebackup.py
bahub/bahubapp/handler/mysqlbackup.py
bahub/bahubapp/mapping/__init__.py
bahub/bahubapp/mapping/definitions.py
bahub/bahubapp/mapping/handlers.py
bahub/bahubapp/service/__init__.py
bahub/bahubapp/service/client.py
bahub/bahubapp/service/configurationfactory.py
bahub/bahubapp/service/errorhandler.py
bahub/bahubapp/service/logger.py
bahub/bahubapp/service/notifier.py
bahub/bahubapp/service/pipefactory.py
bahub-2.0.6.data/data/local/etc/bahub/configuration.yaml.dist
bahub-2.0.6.dist-info/AUTHORS
bahub-2.0.6.dist-info/METADATA
bahub-2.0.6.dist-info/WHEEL
bahub-2.0.6.dist-info/entry_points.txt
bahub-2.0.6.dist-info/pbr.json
bahub-2.0.6.dist-info/top_level.txt
bahub-2.0.6.dist-info/RECORD
