Metadata-Version: 2.1
Name: bahub
Version: 2.0.6
Summary: Bahub is a File Repository API client that allows to totally automate the backups on your server
Home-page: https://github.com/riotkit-org/file-repository
Author: RiotKit Collective
Author-email: marek_andrzejczak@riseup.net
License: MIT
Platform: UNKNOWN
Classifier: Development Status :: 5 - Production/Stable
Classifier: Intended Audience :: Developers
Classifier: Intended Audience :: System Administrators
Classifier: Natural Language :: English
Classifier: Operating System :: POSIX :: Linux
Classifier: Programming Language :: Python :: 3 :: Only
Classifier: Topic :: Utilities
Classifier: Topic :: System :: Systems Administration
Requires-Python: >=3.6
Requires-Dist: PyYAML (>=3.12)
Requires-Dist: pbr (>=5.1)
Requires-Dist: requests (>=2.21)
Requires-Dist: setuptools (>=40.4.3)
Requires-Dist: simplejson (>=3.16)
Requires-Dist: unittest-data-provider
Requires-Dist: coverage
Requires-Dist: sentry-sdk (==0.7.14)
